okayletsgo/__init__.py
okayletsgo/sound.mp3
okayletsgo-1.3.dist-info/METADATA
okayletsgo-1.3.dist-info/WHEEL
okayletsgo-1.3.dist-info/top_level.txt
okayletsgo-1.3.dist-info/RECORD
