Metadata-Version: 2.1
Name: okayletsgo
Version: 1.3
Summary: A simple Python package to play 'Okaaaay let's go!' through your speakers with just one line of code.
Requires-Dist: just-playback
